lksearch/K2Search.py
lksearch/KeplerSearch.py
lksearch/MASTSearch.py
lksearch/TESSSearch.py
lksearch/__init__.py
lksearch/catalogsearch.py
lksearch/config/__init__.py
lksearch/data/catalog_config.json
lksearch/data/short_cadence_month_lookup.csv
lksearch/utils.py
lksearch-1.2.1.dist-info/LICENSE
lksearch-1.2.1.dist-info/METADATA
lksearch-1.2.1.dist-info/WHEEL
lksearch-1.2.1.dist-info/RECORD
