Metadata-Version: 2.3
Name: lksearch
Version: 1.2.1
Summary: A helpful little package to search for TESS/Kepler/K2 data
License: MIT
Author: TESS Science Support Center
Author-email: tesshelp@bigbang.gsfc.nasa.gov
Requires-Python: >=3.9,<4.0
Classifier: License :: OSI Approved :: MIT License
Classifier: Programming Language :: Python :: 3
Classifier: Programming Language :: Python :: 3.9
Classifier: Programming Language :: Python :: 3.10
Classifier: Programming Language :: Python :: 3.11
Classifier: Programming Language :: Python :: 3.12
Classifier: Programming Language :: Python :: 3.13
Requires-Dist: astropy (>=5.0)
Requires-Dist: astroquery (>=0.4.7,<0.5.0)
Requires-Dist: boto3 (>=1.34.25,<2.0.0)
Requires-Dist: numpy (>=1.26.4,<2.0.0)
Requires-Dist: pandas (>=2.2.2,<3.0.0)
Requires-Dist: requests (>=2.31.0,<3.0.0)
Requires-Dist: tesswcs (>=1.4.1)
Requires-Dist: tqdm (>=4.50.0,<5.0.0)
